{
  "fill" : "system-light",
  "groups" : [
    {
      "layers" : [
        {
          "glass" : false,
          "image-name" : "llegoicon2small.png",
          "name" : "llegoicon2small",
          "position" : {
            "scale" : 1.3,
            "translation-in-points" : [
              -35.260641495536674,
              6.086416828918914
            ]
          }
        }
      ],
      "shadow" : {
        "kind" : "neutral",
        "opacity" : 0.5
      },
      "translucency" : {
        "enabled" : true,
        "value" : 0.5
      }
    }
  ],
  "supported-platforms" : {
    "circles" : [
      "watchOS"
    ],
    "squares" : "shared"
  }
}